netease/__init__.py
netease/__main__.py
netease/netease.py
pynetease_finance-0.0.2.dist-info/METADATA
pynetease_finance-0.0.2.dist-info/WHEEL
pynetease_finance-0.0.2.dist-info/top_level.txt
pynetease_finance-0.0.2.dist-info/RECORD
