Metadata-Version: 2.1
Name: pynetease-finance
Version: 0.0.2
Summary: 获取网易财经网站数据。
Home-page: https://github.com/songjian/pynetease-finance
Author: sj
Author-email: songjian@codeorder.cn
Classifier: Programming Language :: Python :: 3
Classifier: License :: OSI Approved :: MIT License
Classifier: Operating System :: OS Independent
Requires-Python: >=3
Requires-Dist: certifi (==2022.6.15)
Requires-Dist: idna (==3.3)
Requires-Dist: numpy (==1.23.1)
Requires-Dist: pandas (==1.4.3)
Requires-Dist: python-dateutil (==2.8.2)
Requires-Dist: charset-normalizer (==2.1.0)
Requires-Dist: pytz (==2022.1)
Requires-Dist: requests (==2.28.1)
Requires-Dist: six (==1.16.0)
Requires-Dist: urllib3 (==1.26.10)
